Metadata-Version: 2.1
Name: discord-colorize
Version: 0.0.5
Summary: A Python module for colorizing text in Discord using ANSI color codes.
Home-page: UNKNOWN
Author: TheOnlyWayUp
Author-email: thedarkdraconian@gmail.com
License: UNKNOWN
Keywords: discord,discord.py,codeblocks,selfbot,ANSI,colored text
Platform: UNKNOWN
Classifier: Development Status :: 5 - Production/Stable
Classifier: Intended Audience :: Developers
Classifier: Programming Language :: Python :: 3
Classifier: Operating System :: Unix
Classifier: Operating System :: MacOS :: MacOS X
Classifier: Operating System :: Microsoft :: Windows
